odoo/addons/stock_lot_is_archived/README.rst
odoo/addons/stock_lot_is_archived/__init__.py
odoo/addons/stock_lot_is_archived/__manifest__.py
odoo/addons/stock_lot_is_archived/data/ir_cron.xml
odoo/addons/stock_lot_is_archived/i18n/it.po
odoo/addons/stock_lot_is_archived/i18n/stock_lot_is_archived.pot
odoo/addons/stock_lot_is_archived/models/__init__.py
odoo/addons/stock_lot_is_archived/models/stock_lot.py
odoo/addons/stock_lot_is_archived/readme/CONTRIBUTORS.rst
odoo/addons/stock_lot_is_archived/readme/DESCRIPTION.rst
odoo/addons/stock_lot_is_archived/readme/USAGE.rst
odoo/addons/stock_lot_is_archived/security/security.xml
odoo/addons/stock_lot_is_archived/static/description/icon.png
odoo/addons/stock_lot_is_archived/static/description/index.html
odoo/addons/stock_lot_is_archived/tests/__init__.py
odoo/addons/stock_lot_is_archived/tests/test_lot_archive.py
odoo/addons/stock_lot_is_archived/views/stock_lot.xml
odoo/addons/stock_lot_is_archived/wizards/__init__.py
odoo/addons/stock_lot_is_archived/wizards/stock_lot_archive.py
odoo_addon_stock_lot_is_archived-16.0.1.0.0.5.dist-info/METADATA
odoo_addon_stock_lot_is_archived-16.0.1.0.0.5.dist-info/WHEEL
odoo_addon_stock_lot_is_archived-16.0.1.0.0.5.dist-info/top_level.txt
odoo_addon_stock_lot_is_archived-16.0.1.0.0.5.dist-info/RECORD
